[
  {
    "name": "引力精准掌控（潮汐制造）",
    "description": "进一步掌控引力，可制造潮汐现象，且该引力掌控能力可推衍应用于其他领域",
    "type": "非凡能力",
    "power": {
      "0": 44400,
      "1": 11100,
      "2": 4440,
      "3": 1480,
      "4": 555,
      "5": 111,
      "-2": 185000,
      "-1": 111000,
      "0.1": 33300,
      "0.3": 22200,
      "0.4": 20350,
      "0.5": 18500,
      "0.8": 14800,
      "0.9": 12950,
      "default": 111
    },
    "damageType": "mystical",
    "targetType": "all",
    "cost": {
      "type": "currentSpirit",
      "amount": 129
    }
  }
]