[
  {
    "name": "欲望特性（成功欲、认可欲）",
    "description": "内心渴望成功，极度希望获得他人认可，该欲望为核心能力触发基础",
    "type": "被动特性"
  },
  {
    "name": "肾上腺素爆发状态",
    "description": "可基于自身对成功与认可的欲望，进入类似「开启小宇宙」的肾上腺素爆发状态，短时间内大幅提升综合能力",
    "type": "非凡能力",
    "isHeal": true,
    "healType": "活力",
    "healValueType": "fixed",
    "healAmt": {
      "0": 88800,
      "1": 22200,
      "2": 8880,
      "3": 2960,
      "4": 1110,
      "5": 444,
      "6": 185,
      "-2": 370000,
      "-1": 222000,
      "0.1": 66600,
      "0.3": 44400,
      "0.4": 40700,
      "0.5": 37000,
      "0.8": 29600,
      "0.9": 25900,
      "default": 185
    },
    "targetType": "self",
    "cost": {
      "type": "currentSpirit",
      "amount": 54
    },
    "effects": [
      {
        "name": "肾上腺素爆发",
        "type": "buff",
        "stat": "attack",
        "valueType": "percentage",
        "power": {
          "0": 25,
          "1": 20,
          "2": 20,
          "3": 15,
          "4": 15,
          "5": 10,
          "6": 10,
          "-2": 30,
          "-1": 30,
          "0.1": 25,
          "0.3": 25,
          "0.4": 25,
          "0.5": 25,
          "0.8": 25,
          "0.9": 25,
          "default": 10
        },
        "duration": 3
      }
    ]
  }
]