[
  {
    "name": "格斗与射击（恐怖计算与精准控制）",
    "description": "获得恐怖的计算能力与精准的控制力，擅长格斗、射击等",
    "type": "非凡能力",
    "damageType": "physical",
    "targetType": "single",
    "power": {
      "0": 44400,
      "1": 11100,
      "2": 4440,
      "3": 1480,
      "4": 555,
      "5": 222,
      "6": 92,
      "7": 37,
      "8": 17,
      "-2": 185000,
      "-1": 111000,
      "0.1": 33300,
      "0.3": 22200,
      "0.4": 20350,
      "0.5": 18500,
      "0.8": 14800,
      "0.9": 12950,
      "default": 17
    },
    "cost": {
      "type": "currentSpirit",
      "amount": 10
    }
  },
  {
    "name": "身体素质增强",
    "description": "与身体相关的各方面素质明显提升",
    "type": "被动特性"
  },
  {
    "name": "占卜与反占卜",
    "description": "具备占卜与反占卜能力",
    "type": "非凡能力"
  }
]
