[
  {
    "name": "灵界涉足与知识",
    "description": "能涉足灵界，掌握大量灵界知识",
    "type": "被动特性"
  },
  {
    "name": "灵界信使招募",
    "description": "能自行招募灵界信使，获得部分灵界生物的帮助",
    "type": "非凡能力"
  },
  {
    "name": "死灵驱使",
    "description": "可提前控制并驱使亡者、自然灵战斗（需解决灵体跟随、隐藏、抗干扰问题）；实力强弱取决于可驱使的灵体种类，更擅长利用亡者",
    "type": "非凡能力",
    "power": {
      "0": 22200,
      "1": 5550,
      "2": 2220,
      "3": 740,
      "4": 278,
      "5": 111,
      "6": 46,
      "-2": 92500,
      "-1": 55500,
      "0.1": 16650,
      "0.3": 11100,
      "0.4": 10175,
      "0.5": 9250,
      "0.8": 7400,
      "0.9": 6475,
      "default": 46
    },
    "damageType": "mystical",
    "targetType": "all",
    "cost": {
      "type": "currentSpirit",
      "amount": 54
    }
  },
  {
    "name": "复活（死灵唤起）",
    "description": "可唤起活尸与骷髅，此类「复活」无意志与生命力，仅为战斗傀儡",
    "type": "非凡能力"
  },
  {
    "name": "亡者之语",
    "description": "专属语言，可绕过血肉保护，将灵体沟通升级为驱使甚至奴役",
    "type": "非凡能力"
  },
  {
    "name": "死灵克制",
    "description": "克制活尸、怨魂，可有效针对恶灵；能直接控制无主、位格相近的亡者群体；面对同途径高位者时，自身奴仆易叛变",
    "type": "被动特性"
  }
]